{"channelImages": [{"importKeyword": "_w10 Brightfield", "color": "GREY", "axesInterpretation": "Z", "name": "BF", "rgb": "R"}, {"importKeyword": "_w2TIRF 561", "color": "GREY", "axesInterpretation": "TIME", "name": "RecB", "rgb": "R"}], "template": {"trimFrames": [0.0, 0.0], "transformations": [{"outputChannel": [0], "pluginName": "CropTransmittedLightZStack", "params": [{"Slice Selection": {"action": "INTERVAL", "params": [{"Frame interval": [3.0, 7.0]}, {"Step": 1}, {"Include slices over focus": "false"}]}}, {"Focus Selection": {"action": "MANUAL", "params": [{"Center slice": 8}]}}]}, {"outputChannel": [1], "pluginName": "DLFilterSimple", "params": [{"DLEngine": {"pluginName": "TF2engine", "params": [{"Tensorflow model": {"file": ["..\\DLModels\\G1_230425_sample1_8"], "id": "b6361f0a16115dd597885477f4c66786"}}, {"Batch Size": 16}, {"Average Flipped predictions": [0, 0]}, {"Z-Axis": {"action": "BATCH"}}, {"Half Precision": "false"}]}}, {"Input Frame Index": "false"}, {"ResizeAndScale": {"action": "PAD", "params": [{"Resize Shape": [0, 0]}, {"Total Shape Contraction": [8, 8]}, {"Padding Mode": "MIRROR"}, {"Minimum Padding": [0, 0]}, {"Input Scaler": {"pluginName": "ConstantScaler", "params": [{"Scale factor": 626.902}, {"Center": 3499.5}, {"Saturate": "false"}]}}, {"Output Scaling": ["true"]}, {"Scale Image by Image": "false"}]}}, {"Batch Size": 4}, {"Channel": 0}, {"Timelapse": {"action": "true", "params": [{"Next": "true"}, {"Frame Number": 1}, {"Out-of-bounds policy": "MIRROR"}, {"Frame sub-sampling average": []}]}}]}], "frameDuration": 2.0, "useImageScale": "Use Image Calibration", "scaleXY": 1, "scaleZ": 1}, "note": "", "bestFocusPlane": [{"Channel": [0]}, {"Algorithm": {"pluginName": "SelectBestFocusPlane", "params": [{"Pre-Filters": []}, {"Gradient Scale": 3}, {"Smooth Scale": 2}, {"Signal Exclusion Threshold": {"pluginName": "BackgroundThresholder", "params": [{"Sigma factor": 2.5}, {"Final Sigma factor": 3.0}, {"Iteration number": 3}, {"Starting value": {"pluginName": "NO SELECTION"}}]}}, {"Exclude under Threshold": "true"}]}}], "imagePath": ["Output"], "outputPath": ["Output"], "channelImagesDuplicated": [{"name": "RecB_raw", "source": [1]}], "structures": [{"manualPostFilters": [], "channelImage": [0], "trackDisplay": "DEFAULT", "allowSplit": "yes", "allowMerge": "no", "objectSplitter": {"pluginName": "NO SELECTION"}, "scaler": {"pluginName": "NO SELECTION"}, "name": "Bacteria_large", "manualSegmenter": {"pluginName": "NO SELECTION"}, "segmentationParent": [], "parentStructure": [], "displayColor": "MAGENTA", "processingScheme": {"pluginName": "SegmentThenTrack", "params": [{"Pre-Filters": []}, {"Track Pre-Filters": []}, {"Segmentation algorithm": {"pluginName": "ProbabilityMapSegmenter", "params": [{"Predict Probability": {"action": "true", "params": [{"model": {"pluginName": "TF2engine", "params": [{"Tensorflow model": {"file": ["..\\..\\DLModels\\TaLiSSMan_bact_agarpad"], "id": ""}}, {"Batch Size": 16}, {"Average Flipped predictions": [0, 0]}, {"Z-Axis": {"action": "CHANNEL", "params": [{"Channel Index": 0}]}}, {"Half Precision": "false"}]}}, {"ResizeAndScale": {"action": "PAD", "params": [{"Resize Shape": [0, 0]}, {"Total Shape Contraction": [8, 8]}, {"Padding Mode": "MIRROR"}, {"Minimum Padding": [0, 0]}, {"Input Scaler": {"pluginName": "ModeSdScaler", "params": [{"Exclude Mode at Left Tail": 0}, {"Exclude Mode at Right Tail": 0}]}}, {"Output Scaling": ["false"]}, {"Scale Image by Image": "false"}]}}, {"Channel": 0}]}}, {"Split Threshold": 1.43}, {"Minimal Probability": 0.9}, {"Minimal Size": 10}, {"Minimal Max Proba value": 2.5}]}}, {"Post-Filters": [{"pluginName": "Dilate", "params": [{"Radius": {"scaleXY": 2.0, "scaleZ": 1.0, "useImageCalibration": "false"}}]}, {"pluginName": "FeatureFilter", "params": [{"Feature": {"pluginName": "EdgeContact", "params": [{"X left": "true"}, {"X right": "true"}, {"Y up": "true"}, {"Y down": "true"}, {"Z bottom": "false"}, {"Z top": "false"}, {"Normalization": "NONE"}]}}, {"Threshold": 1.0}, {"Keep over threshold": "false"}, {"Strict comparison with threshold": "true"}, {"Use Pre-filtered Image": "true"}, {"Pre-Filters": []}]}]}, {"Tracker": {"pluginName": "LAPTracker", "params": [{"Maximal Distance for Frame-to-Frame Tracking": 100.0}, {"Distance": {"action": "GEOM_CENTER_DISTANCE"}}, {"Detect Split": "true"}, {"Detect Merge": "false"}, {"Allow Gaps": {"action": "false"}}, {"Parent Landmark": "true"}]}}, {"Track Post-Filters": []}]}}, {"manualPostFilters": [], "channelImage": [1], "trackDisplay": "DEFAULT", "allowSplit": "no", "allowMerge": "no", "objectSplitter": {"pluginName": "NO SELECTION"}, "scaler": {"pluginName": "NO SELECTION"}, "name": "RecB_spots", "manualSegmenter": {"pluginName": "NO SELECTION"}, "segmentationParent": [0], "parentStructure": [0], "displayColor": "CYAN", "processingScheme": {"pluginName": "SegmentAndTrack", "params": [{"Pre-Filters": []}, {"Track Pre-Filters": []}, {"Tracker": {"pluginName": "NestedSpotTracker", "params": [{"Segmentation algorithm": {"pluginName": "SpotSegmenter", "params": [{"Scale": [1.0]}, {"Smooth Scale": [0.0]}, {"Min. Spot Size": 7}, {"Seed Laplacian Threshold": 8.0}, {"Propagation Threshold": 8.0}, {"Seed Threshold": 1.0}, {"Intensity normalization": "PER_CELL_CENTER_SCALE"}, {"Quality Formula": "GL"}, {"Watershed Map": "LAPLACIAN"}]}}, {"Bacteria Object Class": [0]}, {"Bacteria Growth Mode": "PROPORTIONAL"}, {"Correct Rotation": "true"}, {"Maximum Linking Distance (FTF)": 0.4}, {"Maximum Linking Distance": 0.4}, {"Maximum Frame Gap": 0}, {"Gap Distance Penalty": 0.15}, {"Use calibrated distance": "true"}, {"Spot Quality Threshold": 8.0}, {"Allow splitting": "false"}, {"Allow merging": "false"}]}}, {"Post-Filters": []}, {"Track Post-Filters": []}]}}, {"manualPostFilters": [], "channelImage": [2], "trackDisplay": "DEFAULT", "allowSplit": "no", "allowMerge": "no", "objectSplitter": {"pluginName": "NO SELECTION"}, "scaler": {"pluginName": "NO SELECTION"}, "name": "RecB_raw", "manualSegmenter": {"pluginName": "NO SELECTION"}, "segmentationParent": [0], "parentStructure": [0], "displayColor": "ORANGE", "processingScheme": {"pluginName": "NO SELECTION"}}], "importMethod": {"action": "One File Per Position, Channel And Frame", "params": [{"Position Separator": "Im"}, {"Frame Separator": "_t"}]}, "positions": [{"defaultFrame": 0, "images": {"fromOmero": true, "positionName": "Im001", "frameNumber": 50, "singleFrameC": [true, false], "invertTZ_CT": {"0;0": false, "1;39": false, "1;30": false, "1;38": false, "1;37": false, "1;36": false, "1;35": false, "1;34": false, "1;33": false, "1;32": false, "1;31": false, "1;41": false, "1;40": false, "1;49": false, "1;48": false, "1;47": false, "1;46": false, "1;45": false, "1;44": false, "1;43": false, "1;42": false, "1;19": false, "1;0": false, "1;18": false, "1;1": false, "1;17": false, "1;2": false, "1;3": false, "1;4": false, "1;5": false, "1;6": false, "1;7": false, "1;8": false, "1;9": false, "1;16": false, "1;15": false, "1;14": false, "1;13": false, "1;12": false, "1;11": false, "1;10": false, "1;29": false, "1;28": false, "1;27": false, "1;26": false, "1;25": false, "1;24": false, "1;23": false, "1;22": false, "1;21": false, "1;20": false}, "channelNumber": 2, "sizeZC": [16, 1], "omeroID_c1": ["1164435", "1164436", "1164437", "1164438", "1164439", "1164440", "1164441", "1164442", "1164443", "1164444", "1164445", "1164446", "1164447", "1164448", "1164449", "1164450", "1164451", "1164452", "1164453", "1164454", "1164455", "1164456", "1164457", "1164458", "1164459", "1164460", "1164461", "1164462", "1164463", "1164464", "1164465", "1164466", "1164467", "1164468", "1164469", "1164470", "1164471", "1164472", "1164473", "1164474", "1164475", "1164476", "1164477", "1164478", "1164479", "1164480", "1164481", "1164482", "1164483", "1164484"], "timePointCZT": {"0;10;0": 1709302830207.0, "1;0;42": 94546.0, "1;0;41": 92542.0, "1;0;40": 90631.0, "1;0;46": 102552.0, "1;0;45": 100577.0, "1;0;44": 98587.0, "1;0;43": 96551.0, "1;0;49": 109073.0, "1;0;48": 107084.0, "1;0;47": 105078.0, "0;3;0": 1709302830207.0, "0;5;0": 1709302830207.0, "1;0;31": 72567.0, "0;7;0": 1709302830207.0, "1;0;30": 70104.0, "0;2;0": 1709302830207.0, "0;9;0": 1709302830207.0, "1;0;35": 80574.0, "0;0;0": 1709302830207.0, "1;0;34": 78568.0, "1;0;33": 76577.0, "1;0;32": 74573.0, "1;0;39": 88594.0, "1;0;38": 86527.0, "1;0;37": 84600.0, "1;0;36": 82594.0, "0;15;0": 1709302830207.0, "0;13;0": 1709302830207.0, "0;11;0": 1709302830207.0, "1;0;20": 49580.0, "1;0;24": 58044.0, "1;0;23": 56039.0, "1;0;22": 54033.0, "1;0;21": 51601.0, "1;0;28": 66047.0, "1;0;27": 64090.0, "1;0;26": 62069.0, "1;0;25": 60048.0, "1;0;29": 68053.0, "1;0;3": 13595.0, "1;0;4": 15696.0, "1;0;1": 8684.0, "1;0;2": 11084.0, "1;0;0": 0.0, "0;4;0": 1709302830207.0, "0;6;0": 1709302830207.0, "0;8;0": 1709302830207.0, "0;1;0": 1709302830207.0, "1;0;13": 34548.0, "1;0;12": 32052.0, "1;0;11": 30064.0, "1;0;10": 28057.0, "1;0;17": 43074.0, "1;0;16": 41069.0, "1;0;9": 26038.0, "1;0;15": 38574.0, "1;0;14": 36553.0, "1;0;7": 21694.0, "1;0;8": 23684.0, "1;0;5": 17635.0, "1;0;19": 47574.0, "1;0;6": 19689.0, "1;0;18": 45064.0, "0;14;0": 1709302830207.0, "0;12;0": 1709302830207.0}, "omeroID_c0": ["1164485"], "scaleXY": 0.106915, "scaleZ": 0.2}, "preProcessingChain": {"trimFrames": [0.0, 0.0], "transformations": [{"outputChannel": [0], "pluginName": "CropTransmittedLightZStack", "params": [{"Slice Selection": {"action": "INTERVAL", "params": [{"Frame interval": [3.0, 7.0]}, {"Step": 1}, {"Include slices over focus": "false"}]}}, {"Focus Selection": {"action": "MANUAL", "params": [{"Center slice": 8}]}}]}, {"outputChannel": [1], "pluginName": "DLFilterSimple", "params": [{"DLEngine": {"pluginName": "TF2engine", "params": [{"Tensorflow model": {"file": ["..\\DLModels\\G1_230425_sample1_8"], "id": "b6361f0a16115dd597885477f4c66786"}}, {"Batch Size": 16}, {"Average Flipped predictions": [0, 0]}, {"Z-Axis": {"action": "BATCH"}}, {"Half Precision": "false"}]}}, {"Input Frame Index": "false"}, {"ResizeAndScale": {"action": "PAD", "params": [{"Resize Shape": [0, 0]}, {"Total Shape Contraction": [8, 8]}, {"Padding Mode": "MIRROR"}, {"Minimum Padding": [0, 0]}, {"Input Scaler": {"pluginName": "ConstantScaler", "params": [{"Scale factor": 626.902}, {"Center": 3499.5}, {"Saturate": "false"}]}}, {"Output Scaling": ["true"]}, {"Scale Image by Image": "false"}]}}, {"Batch Size": 4}, {"Channel": 0}, {"Timelapse": {"action": "true", "params": [{"Next": "true"}, {"Frame Number": 1}, {"Out-of-bounds policy": "MIRROR"}, {"Frame sub-sampling average": []}]}}]}], "frameDuration": 2.0, "useImageScale": "Use Image Calibration", "scaleXY": 1, "scaleZ": 1}, "name": "Im001"}, {"defaultFrame": 0, "images": {"fromOmero": true, "positionName": "Im002", "frameNumber": 50, "singleFrameC": [true, false], "invertTZ_CT": {"0;0": false, "1;39": false, "1;30": false, "1;38": false, "1;37": false, "1;36": false, "1;35": false, "1;34": false, "1;33": false, "1;32": false, "1;31": false, "1;41": false, "1;40": false, "1;49": false, "1;48": false, "1;47": false, "1;46": false, "1;45": false, "1;44": false, "1;43": false, "1;42": false, "1;19": false, "1;0": false, "1;18": false, "1;1": false, "1;17": false, "1;2": false, "1;3": false, "1;4": false, "1;5": false, "1;6": false, "1;7": false, "1;8": false, "1;9": false, "1;16": false, "1;15": false, "1;14": false, "1;13": false, "1;12": false, "1;11": false, "1;10": false, "1;29": false, "1;28": false, "1;27": false, "1;26": false, "1;25": false, "1;24": false, "1;23": false, "1;22": false, "1;21": false, "1;20": false}, "channelNumber": 2, "sizeZC": [16, 1], "omeroID_c1": ["1164486", "1164487", "1164488", "1164489", "1164490", "1164491", "1164492", "1164493", "1164494", "1164495", "1164496", "1164497", "1164498", "1164499", "1164500", "1164501", "1164502", "1164503", "1164504", "1164505", "1164506", "1164507", "1164508", "1164509", "1164510", "1164511", "1164512", "1164513", "1164514", "1164515", "1164516", "1164517", "1164518", "1164519", "1164520", "1164521", "1164522", "1164523", "1164524", "1164525", "1164526", "1164527", "1164528", "1164529", "1164530", "1164531", "1164532", "1164533", "1164534", "1164535"], "timePointCZT": {"0;10;0": 1709302958891.0, "1;0;42": 94918.0, "1;0;41": 92991.0, "1;0;40": 90986.0, "1;0;46": 103933.0, "1;0;45": 101945.0, "1;0;44": 99481.0, "1;0;43": 96924.0, "1;0;49": 110441.0, "1;0;48": 107931.0, "1;0;47": 105957.0, "0;3;0": 1709302958891.0, "0;5;0": 1709302958891.0, "1;0;31": 71928.0, "0;7;0": 1709302958891.0, "1;0;30": 69923.0, "0;2;0": 1709302958891.0, "0;9;0": 1709302958891.0, "1;0;35": 80959.0, "0;0;0": 1709302958891.0, "1;0;34": 78448.0, "1;0;33": 75954.0, "1;0;32": 73934.0, "1;0;39": 88996.0, "1;0;38": 86975.0, "1;0;37": 84970.0, "1;0;36": 82980.0, "0;15;0": 1709302958891.0, "0;13;0": 1709302958891.0, "0;11;0": 1709302958891.0, "1;0;20": 48482.0, "1;0;24": 56914.0, "1;0;23": 54987.0, "1;0;22": 52461.0, "1;0;21": 50469.0, "1;0;28": 65959.0, "1;0;27": 63938.0, "1;0;26": 61429.0, "1;0;25": 59471.0, "1;0;29": 67964.0, "1;0;3": 12455.0, "1;0;4": 15469.0, "1;0;1": 8081.0, "1;0;2": 10465.0, "1;0;0": 0.0, "0;4;0": 1709302958891.0, "0;6;0": 1709302958891.0, "0;8;0": 1709302958891.0, "0;1;0": 1709302958891.0, "1;0;13": 33434.0, "1;0;12": 31476.0, "1;0;11": 29423.0, "1;0;10": 27499.0, "1;0;17": 41976.0, "1;0;16": 39955.0, "1;0;9": 25462.0, "1;0;15": 37950.0, "1;0;14": 35944.0, "1;0;7": 21453.0, "1;0;8": 23457.0, "1;0;5": 17489.0, "1;0;19": 45971.0, "1;0;6": 19447.0, "1;0;18": 43935.0, "0;14;0": 1709302958891.0, "0;12;0": 1709302958891.0}, "omeroID_c0": ["1164536"], "scaleXY": 0.106915, "scaleZ": 0.2}, "preProcessingChain": {"trimFrames": [0.0, 0.0], "transformations": [{"outputChannel": [0], "pluginName": "CropTransmittedLightZStack", "params": [{"Slice Selection": {"action": "INTERVAL", "params": [{"Frame interval": [3.0, 7.0]}, {"Step": 1}, {"Include slices over focus": "false"}]}}, {"Focus Selection": {"action": "MANUAL", "params": [{"Center slice": 8}]}}]}, {"outputChannel": [1], "pluginName": "DLFilterSimple", "params": [{"DLEngine": {"pluginName": "TF2engine", "params": [{"Tensorflow model": {"file": ["..\\DLModels\\G1_230425_sample1_8"], "id": "b6361f0a16115dd597885477f4c66786"}}, {"Batch Size": 16}, {"Average Flipped predictions": [0, 0]}, {"Z-Axis": {"action": "BATCH"}}, {"Half Precision": "false"}]}}, {"Input Frame Index": "false"}, {"ResizeAndScale": {"action": "PAD", "params": [{"Resize Shape": [0, 0]}, {"Total Shape Contraction": [8, 8]}, {"Padding Mode": "MIRROR"}, {"Minimum Padding": [0, 0]}, {"Input Scaler": {"pluginName": "ConstantScaler", "params": [{"Scale factor": 626.902}, {"Center": 3499.5}, {"Saturate": "false"}]}}, {"Output Scaling": ["true"]}, {"Scale Image by Image": "false"}]}}, {"Batch Size": 4}, {"Channel": 0}, {"Timelapse": {"action": "true", "params": [{"Next": "true"}, {"Frame Number": 1}, {"Out-of-bounds policy": "MIRROR"}, {"Frame sub-sampling average": []}]}}]}], "frameDuration": 2.0, "useImageScale": "Use Image Calibration", "scaleXY": 1, "scaleZ": 1}, "name": "Im002"}, {"defaultFrame": 0, "images": {"fromOmero": true, "positionName": "Im003", "frameNumber": 50, "singleFrameC": [true, false], "invertTZ_CT": {"0;0": false, "1;39": false, "1;30": false, "1;38": false, "1;37": false, "1;36": false, "1;35": false, "1;34": false, "1;33": false, "1;32": false, "1;31": false, "1;41": false, "1;40": false, "1;49": false, "1;48": false, "1;47": false, "1;46": false, "1;45": false, "1;44": false, "1;43": false, "1;42": false, "1;19": false, "1;0": false, "1;18": false, "1;1": false, "1;17": false, "1;2": false, "1;3": false, "1;4": false, "1;5": false, "1;6": false, "1;7": false, "1;8": false, "1;9": false, "1;16": false, "1;15": false, "1;14": false, "1;13": false, "1;12": false, "1;11": false, "1;10": false, "1;29": false, "1;28": false, "1;27": false, "1;26": false, "1;25": false, "1;24": false, "1;23": false, "1;22": false, "1;21": false, "1;20": false}, "channelNumber": 2, "sizeZC": [16, 1], "omeroID_c1": ["1164537", "1164538", "1164539", "1164540", "1164541", "1164542", "1164543", "1164544", "1164545", "1164546", "1164547", "1164548", "1164549", "1164550", "1164551", "1164552", "1164553", "1164554", "1164555", "1164556", "1164557", "1164558", "1164559", "1164560", "1164561", "1164562", "1164563", "1164564", "1164565", "1164566", "1164567", "1164568", "1164569", "1164570", "1164571", "1164572", "1164573", "1164574", "1164575", "1164576", "1164577", "1164578", "1164579", "1164580", "1164581", "1164582", "1164583", "1164584", "1164585", "1164586"], "timePointCZT": {"0;10;0": 1709303071766.0, "1;0;42": 94989.0, "1;0;41": 92985.0, "1;0;40": 90473.0, "1;0;46": 103027.0, "1;0;45": 101020.0, "1;0;44": 98999.0, "1;0;43": 96994.0, "1;0;49": 109027.0, "1;0;48": 107037.0, "1;0;47": 105016.0, "0;3;0": 1709303071766.0, "0;5;0": 1709303071766.0, "1;0;31": 72001.0, "0;7;0": 1709303071766.0, "1;0;30": 69505.0, "0;2;0": 1709303071766.0, "0;9;0": 1709303071766.0, "1;0;35": 80007.0, "0;0;0": 1709303071766.0, "1;0;34": 78033.0, "1;0;33": 75996.0, "1;0;32": 74006.0, "1;0;39": 88074.0, "1;0;38": 86070.0, "1;0;37": 84064.0, "1;0;36": 82043.0, "0;15;0": 1709303071766.0, "0;13;0": 1709303071766.0, "0;11;0": 1709303071766.0, "1;0;20": 48017.0, "1;0;24": 56970.0, "1;0;23": 54964.0, "1;0;22": 52959.0, "1;0;21": 50527.0, "1;0;28": 64989.0, "1;0;27": 63015.0, "1;0;26": 60980.0, "1;0;25": 58975.0, "1;0;29": 67485.0, "1;0;3": 12460.0, "1;0;4": 14528.0, "1;0;1": 8605.0, "1;0;2": 10501.0, "1;0;0": 0.0, "0;4;0": 1709303071766.0, "0;6;0": 1709303071766.0, "0;8;0": 1709303071766.0, "0;1;0": 1709303071766.0, "1;0;13": 33003.0, "1;0;12": 30540.0, "1;0;11": 28534.0, "1;0;10": 26528.0, "1;0;17": 42002.0, "1;0;16": 39997.0, "1;0;9": 24507.0, "1;0;15": 37502.0, "1;0;14": 35512.0, "1;0;7": 20496.0, "1;0;8": 22487.0, "1;0;5": 16470.0, "1;0;19": 46028.0, "1;0;6": 18492.0, "1;0;18": 44008.0, "0;14;0": 1709303071766.0, "0;12;0": 1709303071766.0}, "omeroID_c0": ["1164587"], "scaleXY": 0.106915, "scaleZ": 0.2}, "preProcessingChain": {"trimFrames": [0.0, 0.0], "transformations": [{"outputChannel": [0], "pluginName": "CropTransmittedLightZStack", "params": [{"Slice Selection": {"action": "INTERVAL", "params": [{"Frame interval": [3.0, 7.0]}, {"Step": 1}, {"Include slices over focus": "false"}]}}, {"Focus Selection": {"action": "MANUAL", "params": [{"Center slice": 8}]}}]}, {"outputChannel": [1], "pluginName": "DLFilterSimple", "params": [{"DLEngine": {"pluginName": "TF2engine", "params": [{"Tensorflow model": {"file": ["..\\DLModels\\G1_230425_sample1_8"], "id": "b6361f0a16115dd597885477f4c66786"}}, {"Batch Size": 16}, {"Average Flipped predictions": [0, 0]}, {"Z-Axis": {"action": "BATCH"}}, {"Half Precision": "false"}]}}, {"Input Frame Index": "false"}, {"ResizeAndScale": {"action": "PAD", "params": [{"Resize Shape": [0, 0]}, {"Total Shape Contraction": [8, 8]}, {"Padding Mode": "MIRROR"}, {"Minimum Padding": [0, 0]}, {"Input Scaler": {"pluginName": "ConstantScaler", "params": [{"Scale factor": 626.902}, {"Center": 3499.5}, {"Saturate": "false"}]}}, {"Output Scaling": ["true"]}, {"Scale Image by Image": "false"}]}}, {"Batch Size": 4}, {"Channel": 0}, {"Timelapse": {"action": "true", "params": [{"Next": "true"}, {"Frame Number": 1}, {"Out-of-bounds policy": "MIRROR"}, {"Frame sub-sampling average": []}]}}]}], "frameDuration": 2.0, "useImageScale": "Use Image Calibration", "scaleXY": 1, "scaleZ": 1}, "name": "Im003"}, {"defaultFrame": 0, "images": {"fromOmero": true, "positionName": "Im004", "frameNumber": 50, "singleFrameC": [true, false], "invertTZ_CT": {"0;0": false, "1;39": false, "1;30": false, "1;38": false, "1;37": false, "1;36": false, "1;35": false, "1;34": false, "1;33": false, "1;32": false, "1;31": false, "1;41": false, "1;40": false, "1;49": false, "1;48": false, "1;47": false, "1;46": false, "1;45": false, "1;44": false, "1;43": false, "1;42": false, "1;19": false, "1;0": false, "1;18": false, "1;1": false, "1;17": false, "1;2": false, "1;3": false, "1;4": false, "1;5": false, "1;6": false, "1;7": false, "1;8": false, "1;9": false, "1;16": false, "1;15": false, "1;14": false, "1;13": false, "1;12": false, "1;11": false, "1;10": false, "1;29": false, "1;28": false, "1;27": false, "1;26": false, "1;25": false, "1;24": false, "1;23": false, "1;22": false, "1;21": false, "1;20": false}, "channelNumber": 2, "sizeZC": [16, 1], "omeroID_c1": ["1164588", "1164589", "1164590", "1164591", "1164592", "1164593", "1164594", "1164595", "1164596", "1164597", "1164598", "1164599", "1164600", "1164601", "1164602", "1164603", "1164604", "1164605", "1164606", "1164607", "1164608", "1164609", "1164610", "1164611", "1164612", "1164613", "1164614", "1164615", "1164616", "1164617", "1164618", "1164619", "1164620", "1164621", "1164622", "1164623", "1164624", "1164625", "1164626", "1164627", "1164628", "1164629", "1164630", "1164631", "1164632", "1164633", "1164634", "1164635", "1164636", "1164637"], "timePointCZT": {"0;10;0": 1709303183760.0, "1;0;42": 93497.0, "1;0;41": 91491.0, "1;0;40": 89454.0, "1;0;46": 102497.0, "1;0;45": 100002.0, "1;0;44": 97980.0, "1;0;43": 95502.0, "1;0;49": 109018.0, "1;0;48": 106996.0, "1;0;47": 104487.0, "0;3;0": 1709303183760.0, "0;5;0": 1709303183760.0, "1;0;31": 71440.0, "0;7;0": 1709303183760.0, "1;0;30": 69482.0, "0;2;0": 1709303183760.0, "0;9;0": 1709303183760.0, "1;0;35": 79460.0, "0;0;0": 1709303183760.0, "1;0;34": 77518.0, "1;0;33": 75497.0, "1;0;32": 73523.0, "1;0;39": 87481.0, "1;0;38": 85460.0, "1;0;37": 83487.0, "1;0;36": 81481.0, "0;15;0": 1709303183760.0, "0;13;0": 1709303183760.0, "0;11;0": 1709303183760.0, "1;0;20": 49017.0, "1;0;24": 57481.0, "1;0;23": 55492.0, "1;0;22": 53470.0, "1;0;21": 51463.0, "1;0;28": 65471.0, "1;0;27": 63497.0, "1;0;26": 61492.0, "1;0;25": 59502.0, "1;0;29": 67508.0, "1;0;3": 11952.0, "1;0;4": 13953.0, "1;0;1": 8021.0, "1;0;2": 10026.0, "1;0;0": 0.0, "0;4;0": 1709303183760.0, "0;6;0": 1709303183760.0, "0;8;0": 1709303183760.0, "0;1;0": 1709303183760.0, "1;0;13": 34477.0, "1;0;12": 32472.0, "1;0;11": 29977.0, "1;0;10": 26979.0, "1;0;17": 42987.0, "1;0;16": 40981.0, "1;0;9": 24988.0, "1;0;15": 39025.0, "1;0;14": 36482.0, "1;0;7": 20490.0, "1;0;8": 22495.0, "1;0;5": 16448.0, "1;0;19": 46965.0, "1;0;6": 18484.0, "1;0;18": 44959.0, "0;14;0": 1709303183760.0, "0;12;0": 1709303183760.0}, "omeroID_c0": ["1164638"], "scaleXY": 0.106915, "scaleZ": 0.2}, "preProcessingChain": {"trimFrames": [0.0, 0.0], "transformations": [{"outputChannel": [0], "pluginName": "CropTransmittedLightZStack", "params": [{"Slice Selection": {"action": "INTERVAL", "params": [{"Frame interval": [3.0, 7.0]}, {"Step": 1}, {"Include slices over focus": "false"}]}}, {"Focus Selection": {"action": "MANUAL", "params": [{"Center slice": 8}]}}]}, {"outputChannel": [1], "pluginName": "DLFilterSimple", "params": [{"DLEngine": {"pluginName": "TF2engine", "params": [{"Tensorflow model": {"file": ["..\\DLModels\\G1_230425_sample1_8"], "id": "b6361f0a16115dd597885477f4c66786"}}, {"Batch Size": 16}, {"Average Flipped predictions": [0, 0]}, {"Z-Axis": {"action": "BATCH"}}, {"Half Precision": "false"}]}}, {"Input Frame Index": "false"}, {"ResizeAndScale": {"action": "PAD", "params": [{"Resize Shape": [0, 0]}, {"Total Shape Contraction": [8, 8]}, {"Padding Mode": "MIRROR"}, {"Minimum Padding": [0, 0]}, {"Input Scaler": {"pluginName": "ConstantScaler", "params": [{"Scale factor": 626.902}, {"Center": 3499.5}, {"Saturate": "false"}]}}, {"Output Scaling": ["true"]}, {"Scale Image by Image": "false"}]}}, {"Batch Size": 4}, {"Channel": 0}, {"Timelapse": {"action": "true", "params": [{"Next": "true"}, {"Frame Number": 1}, {"Out-of-bounds policy": "MIRROR"}, {"Frame sub-sampling average": []}]}}]}], "frameDuration": 2.0, "useImageScale": "Use Image Calibration", "scaleXY": 1, "scaleZ": 1}, "name": "Im004"}, {"defaultFrame": 0, "images": {"fromOmero": true, "positionName": "Im005", "frameNumber": 50, "singleFrameC": [true, false], "invertTZ_CT": {"0;0": false, "1;39": false, "1;30": false, "1;38": false, "1;37": false, "1;36": false, "1;35": false, "1;34": false, "1;33": false, "1;32": false, "1;31": false, "1;41": false, "1;40": false, "1;49": false, "1;48": false, "1;47": false, "1;46": false, "1;45": false, "1;44": false, "1;43": false, "1;42": false, "1;19": false, "1;0": false, "1;18": false, "1;1": false, "1;17": false, "1;2": false, "1;3": false, "1;4": false, "1;5": false, "1;6": false, "1;7": false, "1;8": false, "1;9": false, "1;16": false, "1;15": false, "1;14": false, "1;13": false, "1;12": false, "1;11": false, "1;10": false, "1;29": false, "1;28": false, "1;27": false, "1;26": false, "1;25": false, "1;24": false, "1;23": false, "1;22": false, "1;21": false, "1;20": false}, "channelNumber": 2, "sizeZC": [16, 1], "omeroID_c1": ["1164639", "1164640", "1164641", "1164642", "1164643", "1164644", "1164645", "1164646", "1164647", "1164648", "1164649", "1164650", "1164651", "1164652", "1164653", "1164654", "1164655", "1164656", "1164657", "1164658", "1164659", "1164660", "1164661", "1164662", "1164663", "1164664", "1164665", "1164666", "1164667", "1164668", "1164669", "1164670", "1164671", "1164672", "1164673", "1164674", "1164675", "1164676", "1164677", "1164678", "1164679", "1164680", "1164681", "1164682", "1164683", "1164684", "1164685", "1164686", "1164687", "1164688"], "timePointCZT": {"0;10;0": 1709303295843.0, "1;0;42": 92959.0, "1;0;41": 90969.0, "1;0;40": 88948.0, "1;0;46": 100916.0, "1;0;45": 98991.0, "1;0;44": 96953.0, "1;0;43": 94948.0, "1;0;49": 107438.0, "1;0;48": 104958.0, "1;0;47": 103000.0, "0;3;0": 1709303295843.0, "0;5;0": 1709303295843.0, "1;0;31": 69923.0, "0;7;0": 1709303295843.0, "1;0;30": 67491.0, "0;2;0": 1709303295843.0, "0;9;0": 1709303295843.0, "1;0;35": 78451.0, "0;0;0": 1709303295843.0, "1;0;34": 76445.0, "1;0;33": 74455.0, "1;0;32": 71913.0, "1;0;39": 86501.0, "1;0;38": 84480.0, "1;0;37": 82490.0, "1;0;36": 80487.0, "0;15;0": 1709303295843.0, "0;13;0": 1709303295843.0, "0;11;0": 1709303295843.0, "1;0;20": 47444.0, "1;0;24": 55461.0, "1;0;23": 53473.0, "1;0;22": 51437.0, "1;0;21": 49432.0, "1;0;28": 63451.0, "1;0;27": 61461.0, "1;0;26": 59455.0, "1;0;25": 57465.0, "1;0;29": 65487.0, "1;0;3": 12441.0, "1;0;4": 14447.0, "1;0;1": 8114.0, "1;0;2": 9947.0, "1;0;0": 0.0, "0;4;0": 1709303295843.0, "0;6;0": 1709303295843.0, "0;8;0": 1709303295843.0, "0;1;0": 1709303295843.0, "1;0;13": 32429.0, "1;0;12": 30487.0, "1;0;11": 28480.0, "1;0;10": 26446.0, "1;0;17": 40940.0, "1;0;16": 38476.0, "1;0;9": 24441.0, "1;0;15": 36456.0, "1;0;14": 34498.0, "1;0;7": 20480.0, "1;0;8": 22452.0, "1;0;5": 16451.0, "1;0;19": 44934.0, "1;0;6": 18474.0, "1;0;18": 42929.0, "0;14;0": 1709303295843.0, "0;12;0": 1709303295843.0}, "omeroID_c0": ["1164689"], "scaleXY": 0.106915, "scaleZ": 0.2}, "preProcessingChain": {"trimFrames": [0.0, 0.0], "transformations": [{"outputChannel": [0], "pluginName": "CropTransmittedLightZStack", "params": [{"Slice Selection": {"action": "INTERVAL", "params": [{"Frame interval": [3.0, 7.0]}, {"Step": 1}, {"Include slices over focus": "false"}]}}, {"Focus Selection": {"action": "MANUAL", "params": [{"Center slice": 8}]}}]}, {"outputChannel": [1], "pluginName": "DLFilterSimple", "params": [{"DLEngine": {"pluginName": "TF2engine", "params": [{"Tensorflow model": {"file": ["..\\DLModels\\G1_230425_sample1_8"], "id": "b6361f0a16115dd597885477f4c66786"}}, {"Batch Size": 16}, {"Average Flipped predictions": [0, 0]}, {"Z-Axis": {"action": "BATCH"}}, {"Half Precision": "false"}]}}, {"Input Frame Index": "false"}, {"ResizeAndScale": {"action": "PAD", "params": [{"Resize Shape": [0, 0]}, {"Total Shape Contraction": [8, 8]}, {"Padding Mode": "MIRROR"}, {"Minimum Padding": [0, 0]}, {"Input Scaler": {"pluginName": "ConstantScaler", "params": [{"Scale factor": 626.902}, {"Center": 3499.5}, {"Saturate": "false"}]}}, {"Output Scaling": ["true"]}, {"Scale Image by Image": "false"}]}}, {"Batch Size": 4}, {"Channel": 0}, {"Timelapse": {"action": "true", "params": [{"Next": "true"}, {"Frame Number": 1}, {"Out-of-bounds policy": "MIRROR"}, {"Frame sub-sampling average": []}]}}]}], "frameDuration": 2.0, "useImageScale": "Use Image Calibration", "scaleXY": 1, "scaleZ": 1}, "name": "Im005"}, {"defaultFrame": 0, "images": {"fromOmero": true, "positionName": "Im006", "frameNumber": 50, "singleFrameC": [true, false], "invertTZ_CT": {"0;0": false, "1;39": false, "1;30": false, "1;38": false, "1;37": false, "1;36": false, "1;35": false, "1;34": false, "1;33": false, "1;32": false, "1;31": false, "1;41": false, "1;40": false, "1;49": false, "1;48": false, "1;47": false, "1;46": false, "1;45": false, "1;44": false, "1;43": false, "1;42": false, "1;19": false, "1;0": false, "1;18": false, "1;1": false, "1;17": false, "1;2": false, "1;3": false, "1;4": false, "1;5": false, "1;6": false, "1;7": false, "1;8": false, "1;9": false, "1;16": false, "1;15": false, "1;14": false, "1;13": false, "1;12": false, "1;11": false, "1;10": false, "1;29": false, "1;28": false, "1;27": false, "1;26": false, "1;25": false, "1;24": false, "1;23": false, "1;22": false, "1;21": false, "1;20": false}, "channelNumber": 2, "sizeZC": [16, 1], "omeroID_c1": ["1164690", "1164691", "1164692", "1164693", "1164694", "1164695", "1164696", "1164697", "1164698", "1164699", "1164700", "1164701", "1164702", "1164703", "1164704", "1164705", "1164706", "1164707", "1164708", "1164709", "1164710", "1164711", "1164712", "1164713", "1164714", "1164715", "1164716", "1164717", "1164718", "1164719", "1164720", "1164721", "1164722", "1164723", "1164724", "1164725", "1164726", "1164727", "1164728", "1164729", "1164730", "1164731", "1164732", "1164733", "1164734", "1164735", "1164736", "1164737", "1164738", "1164739"], "timePointCZT": {"0;10;0": 1709303406250.0, "1;0;42": 94972.0, "1;0;41": 93031.0, "1;0;40": 91041.0, "1;0;46": 103025.0, "1;0;45": 101021.0, "1;0;44": 99031.0, "1;0;43": 96978.0, "1;0;49": 109025.0, "1;0;48": 106987.0, "1;0;47": 105014.0, "0;3;0": 1709303406250.0, "0;5;0": 1709303406250.0, "1;0;31": 71510.0, "0;7;0": 1709303406250.0, "1;0;30": 69488.0, "0;2;0": 1709303406250.0, "0;9;0": 1709303406250.0, "1;0;35": 80019.0, "0;0;0": 1709303406250.0, "1;0;34": 78030.0, "1;0;33": 75519.0, "1;0;32": 73531.0, "1;0;39": 89035.0, "1;0;38": 86525.0, "1;0;37": 84030.0, "1;0;36": 82041.0, "0;15;0": 1709303406250.0, "0;13;0": 1709303406250.0, "0;11;0": 1709303406250.0, "1;0;20": 47529.0, "1;0;24": 56007.0, "1;0;23": 53528.0, "1;0;22": 51540.0, "1;0;21": 49503.0, "1;0;28": 63978.0, "1;0;27": 61976.0, "1;0;26": 59986.0, "1;0;25": 57980.0, "1;0;29": 66504.0, "1;0;3": 13012.0, "1;0;4": 15016.0, "1;0;1": 8085.0, "1;0;2": 11006.0, "1;0;0": 0.0, "0;4;0": 1709303406250.0, "0;6;0": 1709303406250.0, "0;8;0": 1709303406250.0, "0;1;0": 1709303406250.0, "1;0;13": 32987.0, "1;0;12": 30997.0, "1;0;11": 29008.0, "1;0;10": 26970.0, "1;0;17": 41024.0, "1;0;16": 39019.0, "1;0;9": 25059.0, "1;0;15": 37029.0, "1;0;14": 35024.0, "1;0;7": 21049.0, "1;0;8": 23039.0, "1;0;5": 17038.0, "1;0;19": 45509.0, "1;0;6": 19027.0, "1;0;18": 43029.0, "0;14;0": 1709303406250.0, "0;12;0": 1709303406250.0}, "omeroID_c0": ["1164740"], "scaleXY": 0.106915, "scaleZ": 0.2}, "preProcessingChain": {"trimFrames": [0.0, 0.0], "transformations": [{"outputChannel": [0], "pluginName": "CropTransmittedLightZStack", "params": [{"Slice Selection": {"action": "INTERVAL", "params": [{"Frame interval": [3.0, 7.0]}, {"Step": 1}, {"Include slices over focus": "false"}]}}, {"Focus Selection": {"action": "MANUAL", "params": [{"Center slice": 8}]}}]}, {"outputChannel": [1], "pluginName": "DLFilterSimple", "params": [{"DLEngine": {"pluginName": "TF2engine", "params": [{"Tensorflow model": {"file": ["..\\DLModels\\G1_230425_sample1_8"], "id": "b6361f0a16115dd597885477f4c66786"}}, {"Batch Size": 16}, {"Average Flipped predictions": [0, 0]}, {"Z-Axis": {"action": "BATCH"}}, {"Half Precision": "false"}]}}, {"Input Frame Index": "false"}, {"ResizeAndScale": {"action": "PAD", "params": [{"Resize Shape": [0, 0]}, {"Total Shape Contraction": [8, 8]}, {"Padding Mode": "MIRROR"}, {"Minimum Padding": [0, 0]}, {"Input Scaler": {"pluginName": "ConstantScaler", "params": [{"Scale factor": 626.902}, {"Center": 3499.5}, {"Saturate": "false"}]}}, {"Output Scaling": ["true"]}, {"Scale Image by Image": "false"}]}}, {"Batch Size": 4}, {"Channel": 0}, {"Timelapse": {"action": "true", "params": [{"Next": "true"}, {"Frame Number": 1}, {"Out-of-bounds policy": "MIRROR"}, {"Frame sub-sampling average": []}]}}]}], "frameDuration": 2.0, "useImageScale": "Use Image Calibration", "scaleXY": 1, "scaleZ": 1}, "name": "Im006"}, {"defaultFrame": 0, "images": {"fromOmero": true, "positionName": "Im007", "frameNumber": 50, "singleFrameC": [true, false], "invertTZ_CT": {"0;0": false, "1;39": false, "1;30": false, "1;38": false, "1;37": false, "1;36": false, "1;35": false, "1;34": false, "1;33": false, "1;32": false, "1;31": false, "1;41": false, "1;40": false, "1;49": false, "1;48": false, "1;47": false, "1;46": false, "1;45": false, "1;44": false, "1;43": false, "1;42": false, "1;19": false, "1;0": false, "1;18": false, "1;1": false, "1;17": false, "1;2": false, "1;3": false, "1;4": false, "1;5": false, "1;6": false, "1;7": false, "1;8": false, "1;9": false, "1;16": false, "1;15": false, "1;14": false, "1;13": false, "1;12": false, "1;11": false, "1;10": false, "1;29": false, "1;28": false, "1;27": false, "1;26": false, "1;25": false, "1;24": false, "1;23": false, "1;22": false, "1;21": false, "1;20": false}, "channelNumber": 2, "sizeZC": [16, 1], "omeroID_c1": ["1164741", "1164742", "1164743", "1164744", "1164745", "1164746", "1164747", "1164748", "1164749", "1164750", "1164751", "1164752", "1164753", "1164754", "1164755", "1164756", "1164757", "1164758", "1164759", "1164760", "1164761", "1164762", "1164763", "1164764", "1164765", "1164766", "1164767", "1164768", "1164769", "1164770", "1164771", "1164772", "1164773", "1164774", "1164775", "1164776", "1164777", "1164778", "1164779", "1164780", "1164781", "1164782", "1164783", "1164784", "1164785", "1164786", "1164787", "1164788", "1164789", "1164790"], "timePointCZT": {"0;10;0": 1709303518242.0, "1;0;42": 91485.0, "1;0;41": 89479.0, "1;0;40": 87522.0, "1;0;46": 99634.0, "1;0;45": 97595.0, "1;0;44": 95528.0, "1;0;43": 93522.0, "1;0;49": 106029.0, "1;0;48": 104008.0, "1;0;47": 102018.0, "0;3;0": 1709303518242.0, "0;5;0": 1709303518242.0, "1;0;31": 69522.0, "0;7;0": 1709303518242.0, "1;0;30": 67516.0, "0;2;0": 1709303518242.0, "0;9;0": 1709303518242.0, "1;0;35": 77558.0, "0;0;0": 1709303518242.0, "1;0;34": 75506.0, "1;0;33": 73500.0, "1;0;32": 71526.0, "1;0;39": 85516.0, "1;0;38": 83526.0, "1;0;37": 81537.0, "1;0;36": 79548.0, "0;15;0": 1709303518242.0, "0;13;0": 1709303518242.0, "0;11;0": 1709303518242.0, "1;0;20": 47525.0, "1;0;24": 55483.0, "1;0;23": 53494.0, "1;0;22": 51472.0, "1;0;21": 49466.0, "1;0;28": 63489.0, "1;0;27": 61484.0, "1;0;26": 59479.0, "1;0;25": 57504.0, "1;0;29": 65495.0, "1;0;3": 12472.0, "1;0;4": 14509.0, "1;0;1": 8100.0, "1;0;2": 10516.0, "1;0;0": 0.0, "0;4;0": 1709303518242.0, "0;6;0": 1709303518242.0, "0;8;0": 1709303518242.0, "0;1;0": 1709303518242.0, "1;0;13": 32494.0, "1;0;12": 30519.0, "1;0;11": 28483.0, "1;0;10": 26509.0, "1;0;17": 41099.0, "1;0;16": 39014.0, "1;0;9": 24503.0, "1;0;15": 37009.0, "1;0;14": 34498.0, "1;0;7": 20462.0, "1;0;8": 22482.0, "1;0;5": 16514.0, "1;0;19": 45519.0, "1;0;6": 18502.0, "1;0;18": 43513.0, "0;14;0": 1709303518242.0, "0;12;0": 1709303518242.0}, "omeroID_c0": ["1164791"], "scaleXY": 0.106915, "scaleZ": 0.2}, "preProcessingChain": {"trimFrames": [0.0, 0.0], "transformations": [{"outputChannel": [0], "pluginName": "CropTransmittedLightZStack", "params": [{"Slice Selection": {"action": "INTERVAL", "params": [{"Frame interval": [3.0, 7.0]}, {"Step": 1}, {"Include slices over focus": "false"}]}}, {"Focus Selection": {"action": "MANUAL", "params": [{"Center slice": 8}]}}]}, {"outputChannel": [1], "pluginName": "DLFilterSimple", "params": [{"DLEngine": {"pluginName": "TF2engine", "params": [{"Tensorflow model": {"file": ["..\\DLModels\\G1_230425_sample1_8"], "id": "b6361f0a16115dd597885477f4c66786"}}, {"Batch Size": 16}, {"Average Flipped predictions": [0, 0]}, {"Z-Axis": {"action": "BATCH"}}, {"Half Precision": "false"}]}}, {"Input Frame Index": "false"}, {"ResizeAndScale": {"action": "PAD", "params": [{"Resize Shape": [0, 0]}, {"Total Shape Contraction": [8, 8]}, {"Padding Mode": "MIRROR"}, {"Minimum Padding": [0, 0]}, {"Input Scaler": {"pluginName": "ConstantScaler", "params": [{"Scale factor": 626.902}, {"Center": 3499.5}, {"Saturate": "false"}]}}, {"Output Scaling": ["true"]}, {"Scale Image by Image": "false"}]}}, {"Batch Size": 4}, {"Channel": 0}, {"Timelapse": {"action": "true", "params": [{"Next": "true"}, {"Frame Number": 1}, {"Out-of-bounds policy": "MIRROR"}, {"Frame sub-sampling average": []}]}}]}], "frameDuration": 2.0, "useImageScale": "Use Image Calibration", "scaleXY": 1, "scaleZ": 1}, "name": "Im007"}, {"defaultFrame": 0, "images": {"fromOmero": true, "positionName": "Im008", "frameNumber": 50, "singleFrameC": [true, false], "invertTZ_CT": {"0;0": false, "1;39": false, "1;30": false, "1;38": false, "1;37": false, "1;36": false, "1;35": false, "1;34": false, "1;33": false, "1;32": false, "1;31": false, "1;41": false, "1;40": false, "1;49": false, "1;48": false, "1;47": false, "1;46": false, "1;45": false, "1;44": false, "1;43": false, "1;42": false, "1;19": false, "1;0": false, "1;18": false, "1;1": false, "1;17": false, "1;2": false, "1;3": false, "1;4": false, "1;5": false, "1;6": false, "1;7": false, "1;8": false, "1;9": false, "1;16": false, "1;15": false, "1;14": false, "1;13": false, "1;12": false, "1;11": false, "1;10": false, "1;29": false, "1;28": false, "1;27": false, "1;26": false, "1;25": false, "1;24": false, "1;23": false, "1;22": false, "1;21": false, "1;20": false}, "channelNumber": 2, "sizeZC": [16, 1], "omeroID_c1": ["1164792", "1164793", "1164794", "1164795", "1164796", "1164797", "1164798", "1164799", "1164800", "1164801", "1164802", "1164803", "1164804", "1164805", "1164806", "1164807", "1164808", "1164809", "1164810", "1164811", "1164812", "1164813", "1164814", "1164815", "1164816", "1164817", "1164818", "1164819", "1164820", "1164821", "1164822", "1164823", "1164824", "1164825", "1164826", "1164827", "1164828", "1164829", "1164830", "1164831", "1164832", "1164833", "1164834", "1164835", "1164836", "1164837", "1164838", "1164839", "1164840", "1164841"], "timePointCZT": {"0;10;0": 1709303627383.0, "1;0;42": 93888.0, "1;0;41": 91883.0, "1;0;40": 89895.0, "1;0;46": 102411.0, "1;0;45": 100375.0, "1;0;44": 97896.0, "1;0;43": 95907.0, "1;0;49": 108916.0, "1;0;48": 106909.0, "1;0;47": 104415.0, "0;3;0": 1709303627383.0, "0;5;0": 1709303627383.0, "1;0;31": 70914.0, "0;7;0": 1709303627383.0, "1;0;30": 68894.0, "0;2;0": 1709303627383.0, "0;9;0": 1709303627383.0, "1;0;35": 79377.0, "0;0;0": 1709303627383.0, "1;0;34": 76851.0, "1;0;33": 74892.0, "1;0;32": 72918.0, "1;0;39": 87351.0, "1;0;38": 85362.0, "1;0;37": 83357.0, "1;0;36": 81351.0, "0;15;0": 1709303627383.0, "0;13;0": 1709303627383.0, "0;11;0": 1709303627383.0, "1;0;20": 48395.0, "1;0;24": 56355.0, "1;0;23": 54444.0, "1;0;22": 52374.0, "1;0;21": 50370.0, "1;0;28": 64377.0, "1;0;27": 62371.0, "1;0;26": 60366.0, "1;0;25": 58376.0, "1;0;29": 66872.0, "1;0;3": 12852.0, "1;0;4": 14856.0, "1;0;1": 8495.0, "1;0;2": 10911.0, "1;0;0": 0.0, "0;4;0": 1709303627383.0, "0;6;0": 1709303627383.0, "0;8;0": 1709303627383.0, "0;1;0": 1709303627383.0, "1;0;13": 33427.0, "1;0;12": 31375.0, "1;0;11": 29415.0, "1;0;10": 27395.0, "1;0;17": 41891.0, "1;0;16": 39886.0, "1;0;9": 25374.0, "1;0;15": 37896.0, "1;0;14": 35906.0, "1;0;7": 20935.0, "1;0;8": 23399.0, "1;0;5": 16893.0, "1;0;19": 46344.0, "1;0;6": 18851.0, "1;0;18": 43927.0, "0;14;0": 1709303627383.0, "0;12;0": 1709303627383.0}, "omeroID_c0": ["1164842"], "scaleXY": 0.106915, "scaleZ": 0.2}, "preProcessingChain": {"trimFrames": [0.0, 0.0], "transformations": [{"outputChannel": [0], "pluginName": "CropTransmittedLightZStack", "params": [{"Slice Selection": {"action": "INTERVAL", "params": [{"Frame interval": [3.0, 7.0]}, {"Step": 1}, {"Include slices over focus": "false"}]}}, {"Focus Selection": {"action": "MANUAL", "params": [{"Center slice": 8}]}}]}, {"outputChannel": [1], "pluginName": "DLFilterSimple", "params": [{"DLEngine": {"pluginName": "TF2engine", "params": [{"Tensorflow model": {"file": ["..\\DLModels\\G1_230425_sample1_8"], "id": "b6361f0a16115dd597885477f4c66786"}}, {"Batch Size": 16}, {"Average Flipped predictions": [0, 0]}, {"Z-Axis": {"action": "BATCH"}}, {"Half Precision": "false"}]}}, {"Input Frame Index": "false"}, {"ResizeAndScale": {"action": "PAD", "params": [{"Resize Shape": [0, 0]}, {"Total Shape Contraction": [8, 8]}, {"Padding Mode": "MIRROR"}, {"Minimum Padding": [0, 0]}, {"Input Scaler": {"pluginName": "ConstantScaler", "params": [{"Scale factor": 626.902}, {"Center": 3499.5}, {"Saturate": "false"}]}}, {"Output Scaling": ["true"]}, {"Scale Image by Image": "false"}]}}, {"Batch Size": 4}, {"Channel": 0}, {"Timelapse": {"action": "true", "params": [{"Next": "true"}, {"Frame Number": 1}, {"Out-of-bounds policy": "MIRROR"}, {"Frame sub-sampling average": []}]}}]}], "frameDuration": 2.0, "useImageScale": "Use Image Calibration", "scaleXY": 1, "scaleZ": 1}, "name": "Im008"}, {"defaultFrame": 0, "images": {"fromOmero": true, "positionName": "Im009", "frameNumber": 50, "singleFrameC": [true, false], "invertTZ_CT": {"0;0": false, "1;39": false, "1;30": false, "1;38": false, "1;37": false, "1;36": false, "1;35": false, "1;34": false, "1;33": false, "1;32": false, "1;31": false, "1;41": false, "1;40": false, "1;49": false, "1;48": false, "1;47": false, "1;46": false, "1;45": false, "1;44": false, "1;43": false, "1;42": false, "1;19": false, "1;0": false, "1;18": false, "1;1": false, "1;17": false, "1;2": false, "1;3": false, "1;4": false, "1;5": false, "1;6": false, "1;7": false, "1;8": false, "1;9": false, "1;16": false, "1;15": false, "1;14": false, "1;13": false, "1;12": false, "1;11": false, "1;10": false, "1;29": false, "1;28": false, "1;27": false, "1;26": false, "1;25": false, "1;24": false, "1;23": false, "1;22": false, "1;21": false, "1;20": false}, "channelNumber": 2, "sizeZC": [16, 1], "omeroID_c1": ["1164843", "1164844", "1164845", "1164846", "1164847", "1164848", "1164849", "1164850", "1164851", "1164852", "1164853", "1164854", "1164855", "1164856", "1164857", "1164858", "1164859", "1164860", "1164861", "1164862", "1164863", "1164864", "1164865", "1164866", "1164867", "1164868", "1164869", "1164870", "1164871", "1164872", "1164873", "1164874", "1164875", "1164876", "1164877", "1164878", "1164879", "1164880", "1164881", "1164882", "1164883", "1164884", "1164885", "1164886", "1164887", "1164888", "1164889", "1164890", "1164891", "1164892"], "timePointCZT": {"0;10;0": 1709303739330.0, "1;0;42": 92999.0, "1;0;41": 90962.0, "1;0;40": 88988.0, "1;0;46": 101479.0, "1;0;45": 99505.0, "1;0;44": 97483.0, "1;0;43": 95493.0, "1;0;49": 107985.0, "1;0;48": 105948.0, "1;0;47": 103941.0, "0;3;0": 1709303739330.0, "0;5;0": 1709303739330.0, "1;0;31": 70514.0, "0;7;0": 1709303739330.0, "1;0;30": 68430.0, "0;2;0": 1709303739330.0, "0;9;0": 1709303739330.0, "1;0;35": 78978.0, "0;0;0": 1709303739330.0, "1;0;34": 76956.0, "1;0;33": 74935.0, "1;0;32": 72945.0, "1;0;39": 86981.0, "1;0;38": 84946.0, "1;0;37": 82956.0, "1;0;36": 80982.0, "0;15;0": 1709303739330.0, "0;13;0": 1709303739330.0, "0;11;0": 1709303739330.0, "1;0;20": 47952.0, "1;0;24": 55988.0, "1;0;23": 53968.0, "1;0;22": 51979.0, "1;0;21": 49941.0, "1;0;28": 64421.0, "1;0;27": 62479.0, "1;0;26": 60489.0, "1;0;25": 57994.0, "1;0;29": 66504.0, "1;0;3": 12979.0, "1;0;4": 14968.0, "1;0;1": 8558.0, "1;0;2": 10975.0, "1;0;0": 0.0, "0;4;0": 1709303739330.0, "0;6;0": 1709303739330.0, "0;8;0": 1709303739330.0, "0;1;0": 1709303739330.0, "1;0;13": 34009.0, "1;0;12": 32004.0, "1;0;11": 29999.0, "1;0;10": 27962.0, "1;0;17": 41967.0, "1;0;16": 39962.0, "1;0;9": 26004.0, "1;0;15": 37941.0, "1;0;14": 35935.0, "1;0;7": 21992.0, "1;0;8": 23998.0, "1;0;5": 16958.0, "1;0;19": 45978.0, "1;0;6": 19468.0, "1;0;18": 43972.0, "0;14;0": 1709303739330.0, "0;12;0": 1709303739330.0}, "omeroID_c0": ["1164893"], "scaleXY": 0.106915, "scaleZ": 0.2}, "preProcessingChain": {"trimFrames": [0.0, 0.0], "transformations": [{"outputChannel": [0], "pluginName": "CropTransmittedLightZStack", "params": [{"Slice Selection": {"action": "INTERVAL", "params": [{"Frame interval": [3.0, 7.0]}, {"Step": 1}, {"Include slices over focus": "false"}]}}, {"Focus Selection": {"action": "MANUAL", "params": [{"Center slice": 8}]}}]}, {"outputChannel": [1], "pluginName": "DLFilterSimple", "params": [{"DLEngine": {"pluginName": "TF2engine", "params": [{"Tensorflow model": {"file": ["..\\DLModels\\G1_230425_sample1_8"], "id": "b6361f0a16115dd597885477f4c66786"}}, {"Batch Size": 16}, {"Average Flipped predictions": [0, 0]}, {"Z-Axis": {"action": "BATCH"}}, {"Half Precision": "false"}]}}, {"Input Frame Index": "false"}, {"ResizeAndScale": {"action": "PAD", "params": [{"Resize Shape": [0, 0]}, {"Total Shape Contraction": [8, 8]}, {"Padding Mode": "MIRROR"}, {"Minimum Padding": [0, 0]}, {"Input Scaler": {"pluginName": "ConstantScaler", "params": [{"Scale factor": 626.902}, {"Center": 3499.5}, {"Saturate": "false"}]}}, {"Output Scaling": ["true"]}, {"Scale Image by Image": "false"}]}}, {"Batch Size": 4}, {"Channel": 0}, {"Timelapse": {"action": "true", "params": [{"Next": "true"}, {"Frame Number": 1}, {"Out-of-bounds policy": "MIRROR"}, {"Frame sub-sampling average": []}]}}]}], "frameDuration": 2.0, "useImageScale": "Use Image Calibration", "scaleXY": 1, "scaleZ": 1}, "name": "Im009"}, {"defaultFrame": 0, "images": {"fromOmero": true, "positionName": "Im010", "frameNumber": 50, "singleFrameC": [true, false], "invertTZ_CT": {"0;0": false, "1;39": false, "1;30": false, "1;38": false, "1;37": false, "1;36": false, "1;35": false, "1;34": false, "1;33": false, "1;32": false, "1;31": false, "1;41": false, "1;40": false, "1;49": false, "1;48": false, "1;47": false, "1;46": false, "1;45": false, "1;44": false, "1;43": false, "1;42": false, "1;19": false, "1;0": false, "1;18": false, "1;1": false, "1;17": false, "1;2": false, "1;3": false, "1;4": false, "1;5": false, "1;6": false, "1;7": false, "1;8": false, "1;9": false, "1;16": false, "1;15": false, "1;14": false, "1;13": false, "1;12": false, "1;11": false, "1;10": false, "1;29": false, "1;28": false, "1;27": false, "1;26": false, "1;25": false, "1;24": false, "1;23": false, "1;22": false, "1;21": false, "1;20": false}, "channelNumber": 2, "sizeZC": [16, 1], "omeroID_c1": ["1164894", "1164895", "1164896", "1164897", "1164898", "1164899", "1164900", "1164901", "1164902", "1164903", "1164904", "1164905", "1164906", "1164907", "1164908", "1164909", "1164910", "1164911", "1164912", "1164913", "1164914", "1164915", "1164916", "1164917", "1164918", "1164919", "1164920", "1164921", "1164922", "1164923", "1164924", "1164925", "1164926", "1164927", "1164928", "1164929", "1164930", "1164931", "1164932", "1164933", "1164934", "1164935", "1164936", "1164937", "1164938", "1164939", "1164940", "1164941", "1164942", "1164943"], "timePointCZT": {"0;10;0": 1709303850285.0, "1;0;42": 90965.0, "1;0;41": 89039.0, "1;0;40": 87003.0, "1;0;46": 99049.0, "1;0;45": 96997.0, "1;0;44": 95024.0, "1;0;43": 92956.0, "1;0;49": 104970.0, "1;0;48": 102997.0, "1;0;47": 101008.0, "0;3;0": 1709303850285.0, "0;5;0": 1709303850285.0, "1;0;31": 68467.0, "0;7;0": 1709303850285.0, "1;0;30": 66461.0, "0;2;0": 1709303850285.0, "0;9;0": 1709303850285.0, "1;0;35": 76992.0, "0;0;0": 1709303850285.0, "1;0;34": 74987.0, "1;0;33": 72523.0, "1;0;32": 70473.0, "1;0;39": 85014.0, "1;0;38": 83024.0, "1;0;37": 81001.0, "1;0;36": 78981.0, "0;15;0": 1709303850285.0, "0;13;0": 1709303850285.0, "0;11;0": 1709303850285.0, "1;0;20": 46486.0, "1;0;24": 54492.0, "1;0;23": 52519.0, "1;0;22": 50512.0, "1;0;21": 48507.0, "1;0;28": 62498.0, "1;0;27": 60461.0, "1;0;26": 58456.0, "1;0;25": 56498.0, "1;0;29": 64504.0, "1;0;3": 12014.0, "1;0;4": 14020.0, "1;0;1": 8082.0, "1;0;2": 10009.0, "1;0;0": 0.0, "0;4;0": 1709303850285.0, "0;6;0": 1709303850285.0, "0;8;0": 1709303850285.0, "0;1;0": 1709303850285.0, "1;0;13": 32021.0, "1;0;12": 30017.0, "1;0;11": 28027.0, "1;0;10": 26021.0, "1;0;17": 40470.0, "1;0;16": 38511.0, "1;0;9": 24032.0, "1;0;15": 36018.0, "1;0;14": 34027.0, "1;0;7": 20021.0, "1;0;8": 22026.0, "1;0;5": 16025.0, "1;0;19": 44480.0, "1;0;6": 18032.0, "1;0;18": 42475.0, "0;14;0": 1709303850285.0, "0;12;0": 1709303850285.0}, "omeroID_c0": ["1164944"], "scaleXY": 0.106915, "scaleZ": 0.2}, "preProcessingChain": {"trimFrames": [0.0, 0.0], "transformations": [{"outputChannel": [0], "pluginName": "CropTransmittedLightZStack", "params": [{"Slice Selection": {"action": "INTERVAL", "params": [{"Frame interval": [3.0, 7.0]}, {"Step": 1}, {"Include slices over focus": "false"}]}}, {"Focus Selection": {"action": "MANUAL", "params": [{"Center slice": 8}]}}]}, {"outputChannel": [1], "pluginName": "DLFilterSimple", "params": [{"DLEngine": {"pluginName": "TF2engine", "params": [{"Tensorflow model": {"file": ["..\\DLModels\\G1_230425_sample1_8"], "id": "b6361f0a16115dd597885477f4c66786"}}, {"Batch Size": 16}, {"Average Flipped predictions": [0, 0]}, {"Z-Axis": {"action": "BATCH"}}, {"Half Precision": "false"}]}}, {"Input Frame Index": "false"}, {"ResizeAndScale": {"action": "PAD", "params": [{"Resize Shape": [0, 0]}, {"Total Shape Contraction": [8, 8]}, {"Padding Mode": "MIRROR"}, {"Minimum Padding": [0, 0]}, {"Input Scaler": {"pluginName": "ConstantScaler", "params": [{"Scale factor": 626.902}, {"Center": 3499.5}, {"Saturate": "false"}]}}, {"Output Scaling": ["true"]}, {"Scale Image by Image": "false"}]}}, {"Batch Size": 4}, {"Channel": 0}, {"Timelapse": {"action": "true", "params": [{"Next": "true"}, {"Frame Number": 1}, {"Out-of-bounds policy": "MIRROR"}, {"Frame sub-sampling average": []}]}}]}], "frameDuration": 2.0, "useImageScale": "Use Image Calibration", "scaleXY": 1, "scaleZ": 1}, "name": "Im010"}, {"defaultFrame": 0, "images": {"fromOmero": true, "positionName": "Im011", "frameNumber": 50, "singleFrameC": [true, false], "invertTZ_CT": {"0;0": false, "1;39": false, "1;30": false, "1;38": false, "1;37": false, "1;36": false, "1;35": false, "1;34": false, "1;33": false, "1;32": false, "1;31": false, "1;41": false, "1;40": false, "1;49": false, "1;48": false, "1;47": false, "1;46": false, "1;45": false, "1;44": false, "1;43": false, "1;42": false, "1;19": false, "1;0": false, "1;18": false, "1;1": false, "1;17": false, "1;2": false, "1;3": false, "1;4": false, "1;5": false, "1;6": false, "1;7": false, "1;8": false, "1;9": false, "1;16": false, "1;15": false, "1;14": false, "1;13": false, "1;12": false, "1;11": false, "1;10": false, "1;29": false, "1;28": false, "1;27": false, "1;26": false, "1;25": false, "1;24": false, "1;23": false, "1;22": false, "1;21": false, "1;20": false}, "channelNumber": 2, "sizeZC": [16, 1], "omeroID_c1": ["1164945", "1164946", "1164947", "1164948", "1164949", "1164950", "1164951", "1164952", "1164953", "1164954", "1164955", "1164956", "1164957", "1164958", "1164959", "1164960", "1164961", "1164962", "1164963", "1164964", "1164965", "1164966", "1164967", "1164968", "1164969", "1164970", "1164971", "1164972", "1164973", "1164974", "1164975", "1164976", "1164977", "1164978", "1164979", "1164980", "1164981", "1164982", "1164983", "1164984", "1164985", "1164986", "1164987", "1164988", "1164989", "1164990", "1164991", "1164992", "1164993", "1164994"], "timePointCZT": {"0;10;0": 1709303957798.0, "1;0;42": 90964.0, "1;0;41": 88958.0, "1;0;40": 87033.0, "1;0;46": 99506.0, "1;0;45": 97010.0, "1;0;44": 95006.0, "1;0;43": 92969.0, "1;0;49": 105522.0, "1;0;48": 103501.0, "1;0;47": 101495.0, "0;3;0": 1709303957798.0, "0;5;0": 1709303957798.0, "1;0;31": 68999.0, "0;7;0": 1709303957798.0, "1;0;30": 67011.0, "0;2;0": 1709303957798.0, "0;9;0": 1709303957798.0, "1;0;35": 77022.0, "0;0;0": 1709303957798.0, "1;0;34": 75001.0, "1;0;33": 73026.0, "1;0;32": 71005.0, "1;0;39": 85011.0, "1;0;38": 83021.0, "1;0;37": 81017.0, "1;0;36": 79027.0, "0;15;0": 1709303957798.0, "0;13;0": 1709303957798.0, "0;11;0": 1709303957798.0, "1;0;20": 46534.0, "1;0;24": 54474.0, "1;0;23": 52518.0, "1;0;22": 50545.0, "1;0;21": 48508.0, "1;0;28": 62999.0, "1;0;27": 60979.0, "1;0;26": 58991.0, "1;0;25": 57001.0, "1;0;29": 65004.0, "1;0;3": 12035.0, "1;0;4": 14008.0, "1;0;1": 8085.0, "1;0;2": 10014.0, "1;0;0": 0.0, "0;4;0": 1709303957798.0, "0;6;0": 1709303957798.0, "0;8;0": 1709303957798.0, "0;1;0": 1709303957798.0, "1;0;13": 31978.0, "1;0;12": 29973.0, "1;0;11": 27997.0, "1;0;10": 26008.0, "1;0;17": 40503.0, "1;0;16": 37993.0, "1;0;9": 23988.0, "1;0;15": 36004.0, "1;0;14": 33984.0, "1;0;7": 20007.0, "1;0;8": 22014.0, "1;0;5": 16013.0, "1;0;19": 44498.0, "1;0;6": 17956.0, "1;0;18": 42492.0, "0;14;0": 1709303957798.0, "0;12;0": 1709303957798.0}, "omeroID_c0": ["1164995"], "scaleXY": 0.106915, "scaleZ": 0.2}, "preProcessingChain": {"trimFrames": [0.0, 0.0], "transformations": [{"outputChannel": [0], "pluginName": "CropTransmittedLightZStack", "params": [{"Slice Selection": {"action": "INTERVAL", "params": [{"Frame interval": [3.0, 7.0]}, {"Step": 1}, {"Include slices over focus": "false"}]}}, {"Focus Selection": {"action": "MANUAL", "params": [{"Center slice": 8}]}}]}, {"outputChannel": [1], "pluginName": "DLFilterSimple", "params": [{"DLEngine": {"pluginName": "TF2engine", "params": [{"Tensorflow model": {"file": ["..\\DLModels\\G1_230425_sample1_8"], "id": "b6361f0a16115dd597885477f4c66786"}}, {"Batch Size": 16}, {"Average Flipped predictions": [0, 0]}, {"Z-Axis": {"action": "BATCH"}}, {"Half Precision": "false"}]}}, {"Input Frame Index": "false"}, {"ResizeAndScale": {"action": "PAD", "params": [{"Resize Shape": [0, 0]}, {"Total Shape Contraction": [8, 8]}, {"Padding Mode": "MIRROR"}, {"Minimum Padding": [0, 0]}, {"Input Scaler": {"pluginName": "ConstantScaler", "params": [{"Scale factor": 626.902}, {"Center": 3499.5}, {"Saturate": "false"}]}}, {"Output Scaling": ["true"]}, {"Scale Image by Image": "false"}]}}, {"Batch Size": 4}, {"Channel": 0}, {"Timelapse": {"action": "true", "params": [{"Next": "true"}, {"Frame Number": 1}, {"Out-of-bounds policy": "MIRROR"}, {"Frame sub-sampling average": []}]}}]}], "frameDuration": 2.0, "useImageScale": "Use Image Calibration", "scaleXY": 1, "scaleZ": 1}, "name": "Im011"}, {"defaultFrame": 0, "images": {"fromOmero": true, "positionName": "Im012", "frameNumber": 50, "singleFrameC": [true, false], "invertTZ_CT": {"0;0": false, "1;39": false, "1;30": false, "1;38": false, "1;37": false, "1;36": false, "1;35": false, "1;34": false, "1;33": false, "1;32": false, "1;31": false, "1;41": false, "1;40": false, "1;49": false, "1;48": false, "1;47": false, "1;46": false, "1;45": false, "1;44": false, "1;43": false, "1;42": false, "1;19": false, "1;0": false, "1;18": false, "1;1": false, "1;17": false, "1;2": false, "1;3": false, "1;4": false, "1;5": false, "1;6": false, "1;7": false, "1;8": false, "1;9": false, "1;16": false, "1;15": false, "1;14": false, "1;13": false, "1;12": false, "1;11": false, "1;10": false, "1;29": false, "1;28": false, "1;27": false, "1;26": false, "1;25": false, "1;24": false, "1;23": false, "1;22": false, "1;21": false, "1;20": false}, "channelNumber": 2, "sizeZC": [16, 1], "omeroID_c1": ["1164996", "1164997", "1164998", "1164999", "1165000", "1165001", "1165002", "1165003", "1165004", "1165005", "1165006", "1165007", "1165008", "1165009", "1165010", "1165011", "1165012", "1165013", "1165014", "1165015", "1165016", "1165017", "1165018", "1165019", "1165020", "1165021", "1165022", "1165023", "1165024", "1165025", "1165026", "1165027", "1165028", "1165029", "1165030", "1165031", "1165032", "1165033", "1165034", "1165035", "1165036", "1165037", "1165038", "1165039", "1165040", "1165041", "1165042", "1165043", "1165044", "1165045"], "timePointCZT": {"0;10;0": 1709304065783.0, "1;0;42": 96013.0, "1;0;41": 93975.0, "1;0;40": 92003.0, "1;0;46": 103987.0, "1;0;45": 101997.0, "1;0;44": 100024.0, "1;0;43": 98003.0, "1;0;49": 110017.0, "1;0;48": 108012.0, "1;0;47": 105991.0, "0;3;0": 1709304065783.0, "0;5;0": 1709304065783.0, "1;0;31": 73530.0, "0;7;0": 1709304065783.0, "1;0;30": 71509.0, "0;2;0": 1709304065783.0, "0;9;0": 1709304065783.0, "1;0;35": 81488.0, "0;0;0": 1709304065783.0, "1;0;34": 79451.0, "1;0;33": 77509.0, "1;0;32": 75518.0, "1;0;39": 89998.0, "1;0;38": 87978.0, "1;0;37": 85988.0, "1;0;36": 83983.0, "0;15;0": 1709304065783.0, "0;13;0": 1709304065783.0, "0;11;0": 1709304065783.0, "1;0;20": 49467.0, "1;0;24": 58499.0, "1;0;23": 56510.0, "1;0;22": 53541.0, "1;0;21": 51488.0, "1;0;28": 67499.0, "1;0;27": 65098.0, "1;0;26": 62998.0, "1;0;25": 60488.0, "1;0;29": 69520.0, "1;0;3": 13531.0, "1;0;4": 17051.0, "1;0;1": 8619.0, "1;0;2": 11003.0, "1;0;0": 0.0, "0;4;0": 1709304065783.0, "0;6;0": 1709304065783.0, "0;8;0": 1709304065783.0, "0;1;0": 1709304065783.0, "1;0;13": 35509.0, "1;0;12": 33489.0, "1;0;11": 31500.0, "1;0;10": 28988.0, "1;0;17": 43451.0, "1;0;16": 41493.0, "1;0;9": 27015.0, "1;0;15": 39536.0, "1;0;14": 37499.0, "1;0;7": 22972.0, "1;0;8": 24978.0, "1;0;5": 18978.0, "1;0;19": 47541.0, "1;0;6": 20983.0, "1;0;18": 45471.0, "0;14;0": 1709304065783.0, "0;12;0": 1709304065783.0}, "omeroID_c0": ["1165046"], "scaleXY": 0.106915, "scaleZ": 0.2}, "preProcessingChain": {"trimFrames": [0.0, 0.0], "transformations": [{"outputChannel": [0], "pluginName": "CropTransmittedLightZStack", "params": [{"Slice Selection": {"action": "INTERVAL", "params": [{"Frame interval": [3.0, 7.0]}, {"Step": 1}, {"Include slices over focus": "false"}]}}, {"Focus Selection": {"action": "MANUAL", "params": [{"Center slice": 8}]}}]}, {"outputChannel": [1], "pluginName": "DLFilterSimple", "params": [{"DLEngine": {"pluginName": "TF2engine", "params": [{"Tensorflow model": {"file": ["..\\DLModels\\G1_230425_sample1_8"], "id": "b6361f0a16115dd597885477f4c66786"}}, {"Batch Size": 16}, {"Average Flipped predictions": [0, 0]}, {"Z-Axis": {"action": "BATCH"}}, {"Half Precision": "false"}]}}, {"Input Frame Index": "false"}, {"ResizeAndScale": {"action": "PAD", "params": [{"Resize Shape": [0, 0]}, {"Total Shape Contraction": [8, 8]}, {"Padding Mode": "MIRROR"}, {"Minimum Padding": [0, 0]}, {"Input Scaler": {"pluginName": "ConstantScaler", "params": [{"Scale factor": 626.902}, {"Center": 3499.5}, {"Saturate": "false"}]}}, {"Output Scaling": ["true"]}, {"Scale Image by Image": "false"}]}}, {"Batch Size": 4}, {"Channel": 0}, {"Timelapse": {"action": "true", "params": [{"Next": "true"}, {"Frame Number": 1}, {"Out-of-bounds policy": "MIRROR"}, {"Frame sub-sampling average": []}]}}]}], "frameDuration": 2.0, "useImageScale": "Use Image Calibration", "scaleXY": 1, "scaleZ": 1}, "name": "Im012"}, {"defaultFrame": 0, "images": {"fromOmero": true, "positionName": "Im013", "frameNumber": 50, "singleFrameC": [true, false], "invertTZ_CT": {"0;0": false, "1;39": false, "1;30": false, "1;38": false, "1;37": false, "1;36": false, "1;35": false, "1;34": false, "1;33": false, "1;32": false, "1;31": false, "1;41": false, "1;40": false, "1;49": false, "1;48": false, "1;47": false, "1;46": false, "1;45": false, "1;44": false, "1;43": false, "1;42": false, "1;19": false, "1;0": false, "1;18": false, "1;1": false, "1;17": false, "1;2": false, "1;3": false, "1;4": false, "1;5": false, "1;6": false, "1;7": false, "1;8": false, "1;9": false, "1;16": false, "1;15": false, "1;14": false, "1;13": false, "1;12": false, "1;11": false, "1;10": false, "1;29": false, "1;28": false, "1;27": false, "1;26": false, "1;25": false, "1;24": false, "1;23": false, "1;22": false, "1;21": false, "1;20": false}, "channelNumber": 2, "sizeZC": [16, 1], "omeroID_c1": ["1165047", "1165048", "1165049", "1165050", "1165051", "1165052", "1165053", "1165054", "1165055", "1165056", "1165057", "1165058", "1165059", "1165060", "1165061", "1165062", "1165063", "1165064", "1165065", "1165066", "1165067", "1165068", "1165069", "1165070", "1165071", "1165072", "1165073", "1165074", "1165075", "1165076", "1165077", "1165078", "1165079", "1165080", "1165081", "1165082", "1165083", "1165084", "1165085", "1165086", "1165087", "1165088", "1165089", "1165090", "1165091", "1165092", "1165093", "1165094", "1165095", "1165096"], "timePointCZT": {"0;10;0": 1709304178119.0, "1;0;42": 91195.0, "1;0;41": 89189.0, "1;0;40": 87153.0, "1;0;46": 99705.0, "1;0;45": 97210.0, "1;0;44": 95173.0, "1;0;43": 93182.0, "1;0;49": 105706.0, "1;0;48": 103700.0, "1;0;47": 101694.0, "0;3;0": 1709304178119.0, "0;5;0": 1709304178119.0, "1;0;31": 68728.0, "0;7;0": 1709304178119.0, "1;0;30": 66691.0, "0;2;0": 1709304178119.0, "0;9;0": 1709304178119.0, "1;0;35": 77159.0, "0;0;0": 1709304178119.0, "1;0;34": 75154.0, "1;0;33": 73196.0, "1;0;32": 70733.0, "1;0;39": 85165.0, "1;0;38": 83190.0, "1;0;37": 81186.0, "1;0;36": 79165.0, "0;15;0": 1709304178119.0, "0;13;0": 1709304178119.0, "0;11;0": 1709304178119.0, "1;0;20": 46163.0, "1;0;24": 54691.0, "1;0;23": 52655.0, "1;0;22": 50665.0, "1;0;21": 48691.0, "1;0;28": 62681.0, "1;0;27": 60690.0, "1;0;26": 58670.0, "1;0;25": 56680.0, "1;0;29": 64702.0, "1;0;3": 12153.0, "1;0;4": 14176.0, "1;0;1": 7843.0, "1;0;2": 10195.0, "1;0;0": 0.0, "0;4;0": 1709304178119.0, "0;6;0": 1709304178119.0, "0;8;0": 1709304178119.0, "0;1;0": 1709304178119.0, "1;0;13": 32192.0, "1;0;12": 30201.0, "1;0;11": 28196.0, "1;0;10": 26175.0, "1;0;17": 40148.0, "1;0;16": 38160.0, "1;0;9": 24169.0, "1;0;15": 36218.0, "1;0;14": 34181.0, "1;0;7": 20190.0, "1;0;8": 22195.0, "1;0;5": 16165.0, "1;0;19": 44176.0, "1;0;6": 18170.0, "1;0;18": 42138.0, "0;14;0": 1709304178119.0, "0;12;0": 1709304178119.0}, "omeroID_c0": ["1165097"], "scaleXY": 0.106915, "scaleZ": 0.2}, "preProcessingChain": {"trimFrames": [0.0, 0.0], "transformations": [{"outputChannel": [0], "pluginName": "CropTransmittedLightZStack", "params": [{"Slice Selection": {"action": "INTERVAL", "params": [{"Frame interval": [3.0, 7.0]}, {"Step": 1}, {"Include slices over focus": "false"}]}}, {"Focus Selection": {"action": "MANUAL", "params": [{"Center slice": 8}]}}]}, {"outputChannel": [1], "pluginName": "DLFilterSimple", "params": [{"DLEngine": {"pluginName": "TF2engine", "params": [{"Tensorflow model": {"file": ["..\\DLModels\\G1_230425_sample1_8"], "id": "b6361f0a16115dd597885477f4c66786"}}, {"Batch Size": 16}, {"Average Flipped predictions": [0, 0]}, {"Z-Axis": {"action": "BATCH"}}, {"Half Precision": "false"}]}}, {"Input Frame Index": "false"}, {"ResizeAndScale": {"action": "PAD", "params": [{"Resize Shape": [0, 0]}, {"Total Shape Contraction": [8, 8]}, {"Padding Mode": "MIRROR"}, {"Minimum Padding": [0, 0]}, {"Input Scaler": {"pluginName": "ConstantScaler", "params": [{"Scale factor": 626.902}, {"Center": 3499.5}, {"Saturate": "false"}]}}, {"Output Scaling": ["true"]}, {"Scale Image by Image": "false"}]}}, {"Batch Size": 4}, {"Channel": 0}, {"Timelapse": {"action": "true", "params": [{"Next": "true"}, {"Frame Number": 1}, {"Out-of-bounds policy": "MIRROR"}, {"Frame sub-sampling average": []}]}}]}], "frameDuration": 2.0, "useImageScale": "Use Image Calibration", "scaleXY": 1, "scaleZ": 1}, "name": "Im013"}, {"defaultFrame": 0, "images": {"fromOmero": true, "positionName": "Im015", "frameNumber": 50, "singleFrameC": [true, false], "invertTZ_CT": {"0;0": false, "1;39": false, "1;30": false, "1;38": false, "1;37": false, "1;36": false, "1;35": false, "1;34": false, "1;33": false, "1;32": false, "1;31": false, "1;41": false, "1;40": false, "1;49": false, "1;48": false, "1;47": false, "1;46": false, "1;45": false, "1;44": false, "1;43": false, "1;42": false, "1;19": false, "1;0": false, "1;18": false, "1;1": false, "1;17": false, "1;2": false, "1;3": false, "1;4": false, "1;5": false, "1;6": false, "1;7": false, "1;8": false, "1;9": false, "1;16": false, "1;15": false, "1;14": false, "1;13": false, "1;12": false, "1;11": false, "1;10": false, "1;29": false, "1;28": false, "1;27": false, "1;26": false, "1;25": false, "1;24": false, "1;23": false, "1;22": false, "1;21": false, "1;20": false}, "channelNumber": 2, "sizeZC": [16, 1], "omeroID_c1": ["1165149", "1165150", "1165151", "1165152", "1165153", "1165154", "1165155", "1165156", "1165157", "1165158", "1165159", "1165160", "1165161", "1165162", "1165163", "1165164", "1165165", "1165166", "1165167", "1165168", "1165169", "1165170", "1165171", "1165172", "1165173", "1165174", "1165175", "1165176", "1165177", "1165178", "1165179", "1165180", "1165181", "1165182", "1165183", "1165184", "1165185", "1165186", "1165187", "1165188", "1165189", "1165190", "1165191", "1165192", "1165193", "1165194", "1165195", "1165196", "1165197", "1165198"], "timePointCZT": {"0;10;0": 1709304394052.0, "1;0;42": 90740.0, "1;0;41": 88767.0, "1;0;40": 86762.0, "1;0;46": 98699.0, "1;0;45": 96773.0, "1;0;44": 94752.0, "1;0;43": 92762.0, "1;0;49": 104716.0, "1;0;48": 102709.0, "1;0;47": 100705.0, "0;3;0": 1709304394052.0, "0;5;0": 1709304394052.0, "1;0;31": 68731.0, "0;7;0": 1709304394052.0, "1;0;30": 66694.0, "0;2;0": 1709304394052.0, "0;9;0": 1709304394052.0, "1;0;35": 76752.0, "0;0;0": 1709304394052.0, "1;0;34": 74714.0, "1;0;33": 72709.0, "1;0;32": 70736.0, "1;0;39": 84756.0, "1;0;38": 82719.0, "1;0;37": 80729.0, "1;0;36": 78724.0, "0;15;0": 1709304394052.0, "0;13;0": 1709304394052.0, "0;11;0": 1709304394052.0, "1;0;20": 46231.0, "1;0;24": 54755.0, "1;0;23": 52766.0, "1;0;22": 50746.0, "1;0;21": 48758.0, "1;0;28": 62697.0, "1;0;27": 60598.0, "1;0;26": 58688.0, "1;0;25": 56730.0, "1;0;29": 64704.0, "1;0;3": 12220.0, "1;0;4": 14243.0, "1;0;1": 7830.0, "1;0;2": 10231.0, "1;0;0": 0.0, "0;4;0": 1709304394052.0, "0;6;0": 1709304394052.0, "0;8;0": 1709304394052.0, "0;1;0": 1709304394052.0, "1;0;13": 32210.0, "1;0;12": 30235.0, "1;0;11": 28215.0, "1;0;10": 26226.0, "1;0;17": 40279.0, "1;0;16": 38258.0, "1;0;9": 24188.0, "1;0;15": 36268.0, "1;0;14": 34230.0, "1;0;7": 20227.0, "1;0;8": 22263.0, "1;0;5": 16232.0, "1;0;19": 44274.0, "1;0;6": 18237.0, "1;0;18": 42268.0, "0;14;0": 1709304394052.0, "0;12;0": 1709304394052.0}, "omeroID_c0": ["1165199"], "scaleXY": 0.106915, "scaleZ": 0.2}, "preProcessingChain": {"trimFrames": [0.0, 0.0], "transformations": [{"outputChannel": [0], "pluginName": "CropTransmittedLightZStack", "params": [{"Slice Selection": {"action": "INTERVAL", "params": [{"Frame interval": [3.0, 7.0]}, {"Step": 1}, {"Include slices over focus": "false"}]}}, {"Focus Selection": {"action": "MANUAL", "params": [{"Center slice": 8}]}}]}, {"outputChannel": [1], "pluginName": "DLFilterSimple", "params": [{"DLEngine": {"pluginName": "TF2engine", "params": [{"Tensorflow model": {"file": ["..\\DLModels\\G1_230425_sample1_8"], "id": "b6361f0a16115dd597885477f4c66786"}}, {"Batch Size": 16}, {"Average Flipped predictions": [0, 0]}, {"Z-Axis": {"action": "BATCH"}}, {"Half Precision": "false"}]}}, {"Input Frame Index": "false"}, {"ResizeAndScale": {"action": "PAD", "params": [{"Resize Shape": [0, 0]}, {"Total Shape Contraction": [8, 8]}, {"Padding Mode": "MIRROR"}, {"Minimum Padding": [0, 0]}, {"Input Scaler": {"pluginName": "ConstantScaler", "params": [{"Scale factor": 626.902}, {"Center": 3499.5}, {"Saturate": "false"}]}}, {"Output Scaling": ["true"]}, {"Scale Image by Image": "false"}]}}, {"Batch Size": 4}, {"Channel": 0}, {"Timelapse": {"action": "true", "params": [{"Next": "true"}, {"Frame Number": 1}, {"Out-of-bounds policy": "MIRROR"}, {"Frame sub-sampling average": []}]}}]}], "frameDuration": 2.0, "useImageScale": "Use Image Calibration", "scaleXY": 1, "scaleZ": 1}, "name": "Im015"}], "measurements": [{"pluginName": "ObjectFeatures", "params": [{"Object class": [0]}, {"Pre-Filters": []}, {"Features": [{"pluginName": "Mean", "addParams": [{"Name": "RecBIntensity"}], "params": [{"Intensity": [2]}]}, {"pluginName": "Size", "addParams": [{"Name": "Area"}], "params": [{"Scaled": "Unit"}]}, {"pluginName": "SNR", "addParams": [{"Name": "SNR"}], "params": [{"Intensity": [2]}, {"Background Object Class": []}, {"Formula": "F-B"}, {"Foreground": "mean"}, {"Background": "mean"}, {"Dilatation radius for foreground object": {"scaleXY": 1.0, "scaleZ": 0.0, "useImageCalibration": "false"}}, {"Radius for background mask erosion": {"scaleXY": 1.0, "scaleZ": 0.0, "useImageCalibration": "false"}}]}]}, {"3D measurement": {"action": "SINGLE_PLANE", "params": [{"Plane": 0}]}}]}, {"pluginName": "ObjectInclusionCount", "params": [{"Containing Objects": [0]}, {"Objects to count": [1]}, {"Minimum percentage of inclusion": 100}, {"Count Only TrackHeads": "true"}, {"Measurement Name": "SpotCount"}]}, {"pluginName": "SpineCoordinates", "params": [{"Bacteria": [0]}, {"Spot": [1]}, {"Scaled": "Unit"}, {"Set SpineLength to parent": "false"}]}, {"pluginName": "SpineFeatures", "params": [{"Bacteria": [0]}, {"Scaled": "Unit"}]}, {"pluginName": "BacteriaLineageMeasurements", "params": [{"Object Class": [0]}, {"Lineage Index Name": "BacteriaLineage"}]}, {"pluginName": "SimpleTrackMeasurements", "params": [{"Objects": [1]}]}, {"pluginName": "ObjectFeatures", "params": [{"Object class": [1]}, {"Pre-Filters": []}, {"Features": [{"pluginName": "Mean", "addParams": [{"Name": "Raw_intensity"}], "params": [{"Intensity": [2]}]}]}, {"3D measurement": {"action": "ALL_PLANES"}}]}]}